django_template_check/__init__.py
django_template_check/management/__init__.py
django_template_check/management/commands/__init__.py
django_template_check/management/commands/templatecheck.py
django_template_check-0.4.0.dist-info/LICENSE
django_template_check-0.4.0.dist-info/METADATA
django_template_check-0.4.0.dist-info/WHEEL
django_template_check-0.4.0.dist-info/top_level.txt
django_template_check-0.4.0.dist-info/RECORD
